vimania/__init__.py
vimania/buku.py
vimania/environment.py
vimania/exception.py
vimania/pattern.py
vimania/bms/__init__.py
vimania/bms/handler.py
vimania/db/__init__.py
vimania/db/dal.py
vimania/helper/__init__.py
vimania/helper/mime.py
vimania/helper/position.py
vimania/md/__init__.py
vimania/md/handler.py
vimania/md/mdnav.py
vimania/todos/__init__.py
vimania/todos/cli.py
vimania/todos/handle_buffer.py
vimania/todos/handler.py
vimania/todos/model.py
vimania/vim_/__init__.py
vimania/vim_/compatibility.py
vimania/vim_/vim_helper.py
vimania/vim_/vimania_manager.py
vimania-0.8.2.dist-info/METADATA
vimania-0.8.2.dist-info/WHEEL
vimania-0.8.2.dist-info/entry_points.txt
vimania-0.8.2.dist-info/top_level.txt
vimania-0.8.2.dist-info/RECORD
