Metadata-Version: 2.1
Name: vimania
Version: 0.8.2
Summary: "todo manager with VIM integration"
Home-page: https://github.com/sysid/twbm
Author: sysid
Author-email: sysid@gmx.de
Classifier: Development Status :: 4 - Beta
Classifier: Intended Audience :: Developers
Classifier: License :: OSI Approved :: GNU General Public License v3 (GPLv3)
Classifier: Operating System :: OS Independent
Classifier: Topic :: Utilities
Classifier: Programming Language :: Python :: 3
Classifier: Programming Language :: Python :: 3.9
Requires-Python: >=3.9
Requires-Dist: beautifulsoup4
Requires-Dist: certifi
Requires-Dist: cryptography
Requires-Dist: urllib3
Requires-Dist: html5lib
Requires-Dist: SQLAlchemy
Requires-Dist: alembic
Requires-Dist: typer
Requires-Dist: pydantic[dotenv]
Requires-Dist: requests
Requires-Dist: lxml
Requires-Dist: pure-sql
